{
  "./apps/intermediate/frontend-quiz-app/": {
    "title": "Frontend quiz app solution",
    "bullets": [
      "Select a quiz subject",
      "Select a single answer from each question from a choice of four",
      "See an error message when trying to submit an answer without making a selection"
    ]
  },
  "./apps/intermediate/launch-countdown-timer/": {
    "title": "Launch countdown timer",
    "bullets": [
      "See hover states for all interactive elements on the page",
      "See a live countdown timer that ticks down every second (start the count at 14 days)",
      "Bonus: When a number changes, make the card flip from the middle"
    ]
  },
  "./apps/intermediate/password-generator-app/": {
    "title": "Password generator app solution",
    "bullets": [
      "Generate a password based on the selected inclusion options",
      "Copy the generated password to the computer's clipboard",
      "See a strength rating for their generated password"
    ]
  },
  "./apps/junior/advice-generator-app/": {
    "title": "Advice generator app",
    "bullets": [
      "View the optimal layout for the app depending on their device's screen size",
      "See hover states for all interactive elements on the page",
      "Generate a new piece of advice by clicking the dice icon"
    ]
  },
  "./apps/junior/article-preview-component/": {
    "title": "Article preview component solution",
    "bullets": [
      "Article preview component solution"
    ]
  },
  "./apps/junior/bmi-calculator/": {
    "title": "Body Mass Index Calculator solution",
    "bullets": [
      "Select whether they want to use metric or imperial units",
      "Enter their height and weight",
      "See their BMI result, with their weight classification and healthy weight range"
    ]
  },
  "./apps/junior/character-counter/": {
    "title": "Character counter solution",
    "bullets": [
      "Analyze the character, word, and sentence counts for their text",
      "Exclude/Include spaces in their character count",
      "Set a character limit"
    ]
  },
  "./apps/junior/clipboard-landing-page/": {
    "title": "Clipboard landing page solution",
    "bullets": [
      "View the optimal layout for the site depending on their device's screen size",
      "See hover states for all interactive elements on the page",
      "### Screenshot"
    ]
  },
  "./apps/junior/coding-bootcamp-testimonials-slider/": {
    "title": "Coding bootcamp testimonials slider solution",
    "bullets": [
      "View the optimal layout for the component depending on their device's screen size",
      "Navigate the slider using either their mouse/trackpad or keyboard",
      "### Screenshot"
    ]
  },
  "./apps/junior/conference-ticket-generator/": {
    "title": "Conference ticket generator solution",
    "bullets": [
      "Complete the form with their details",
      "Receive form validation messages if:",
      "- Any field is missed"
    ]
  },
  "./apps/junior/contact-form/": {
    "title": "Contact form solution",
    "bullets": [
      "Complete the form and see a success toast message upon successful submission",
      "Receive form validation messages if:",
      "- A required field has been missed"
    ]
  },
  "./apps/junior/expenses-chart-component/": {
    "title": "Expenses chart component solution",
    "bullets": [
      "View the bar chart and hover over the individual bars to see the correct amounts for each day",
      "See the current day’s bar highlighted in a different colour to the other bars",
      "View the optimal layout for the content depending on their device’s screen size"
    ]
  },
  "./apps/junior/fylo-dark-theme-landing-page/": {
    "title": "Fylo dark theme landing page solution",
    "bullets": [
      "View the optimal layout for the site depending on their device's screen size",
      "See hover states for all interactive elements on the page",
      "### Screenshot"
    ]
  },
  "./apps/junior/fylo-data-storage-component/": {
    "title": "Fylo data storage component solution",
    "bullets": [
      "View the optimal layout for the site depending on their device's screen size",
      "### Screenshot",
      "### Links"
    ]
  },
  "./apps/junior/github-user-search-app/": {
    "title": "GitHub user search app",
    "bullets": [
      "View the optimal layout for the app depending on their device's screen size",
      "See hover states for all interactive elements on the page",
      "Search for GitHub users by their username"
    ]
  },
  "./apps/junior/interactive-card-details-form/": {
    "title": "Interactive card details form solution",
    "bullets": [
      "Fill in the form and see the card details update in real-time",
      "Receive error messages when the form is submitted if:",
      "- Any input field is empty"
    ]
  },
  "./apps/junior/interactive-pricing-component/": {
    "title": "Interactive pricing component solution",
    "bullets": [
      "View the optimal layout for the app depending on their device's screen size",
      "See hover states for all interactive elements on the page",
      "Use the slider and toggle to see prices for different page view numbers"
    ]
  },
  "./apps/junior/loopstudios-landing-page/": {
    "title": "Loopstudios landing page solution",
    "bullets": [
      "View the optimal layout for the site depending on their device's screen size",
      "See hover states for all interactive elements on the page",
      "### Screenshot"
    ]
  },
  "./apps/junior/newsletter-sing-up-with-success-message/": {
    "title": "Newsletter sign-up form with success message solution",
    "bullets": [
      "Newsletter sign-up form with success message solution"
    ]
  },
  "./apps/junior/product-list-with-cart/": {
    "title": "Product list with cart solution",
    "bullets": [
      "Add items to the cart and remove them",
      "Increase/decrease the number of items in the cart",
      "See an order confirmation modal when they click \"Confirm Order\""
    ]
  },
  "./apps/junior/testimonials-grid-section/": {
    "title": "Testimonials grid section solution",
    "bullets": [
      "Testimonials grid section solution"
    ]
  },
  "./apps/junior/time-tracking-dashboard/": {
    "title": "Time tracking dashboard solution",
    "bullets": [
      "Time tracking dashboard solution"
    ]
  },
  "./apps/junior/tip-calculator-app/": {
    "title": "Tip calculator app solution",
    "bullets": [
      "Tip calculator app solution"
    ]
  },
  "./apps/junior/typing-speed-test-main/": {
    "title": "Typing Speed Test",
    "bullets": [
      "Typing Speed Test"
    ]
  },
  "./apps/newbie/3-column-preview-card-component/": {
    "title": "3-column preview card component solution",
    "bullets": [
      "View the optimal layout depending on their device's screen size",
      "See hover states for interactive elements",
      "### Screenshot"
    ]
  },
  "./apps/newbie/blog-preview-card/": {
    "title": "Blog preview card solution",
    "bullets": [
      "Blog preview card solution"
    ]
  },
  "./apps/newbie/equalizer-landing-page/": {
    "title": "Equalizer landing page solution",
    "bullets": [
      "View the optimal layout depending on their device's screen size",
      "See hover states for interactive elements",
      "### Screenshot"
    ]
  },
  "./apps/newbie/faq-accordion/": {
    "title": "FAQ accordion solution",
    "bullets": [
      "Hide/Show the answer to a question when the question is clicked",
      "Navigate the questions and hide/show answers using keyboard navigation alone",
      "View the optimal layout for the interface depending on their device's screen size"
    ]
  },
  "./apps/newbie/four-card-feature-section/": {
    "title": "Four card feature section solution",
    "bullets": [
      "Four card feature section solution"
    ]
  },
  "./apps/newbie/huddle-landingpage-with-single-introductory-section/": {
    "title": "Huddle landing page with single introductory section solution",
    "bullets": [
      "View the optimal layout for the page depending on their device's screen size",
      "See hover states for all interactive elements on the page",
      "### Screenshot"
    ]
  },
  "./apps/newbie/interactive-rating-component/": {
    "title": "Interactive rating component solution",
    "bullets": [
      "View the optimal layout for the app depending on their device's screen size",
      "See hover states for all interactive elements on the page",
      "Select and submit a number rating"
    ]
  },
  "./apps/newbie/intro-component-with-signup-form/": {
    "title": "Intro component with sign up form solution",
    "bullets": [
      "View the optimal layout for the site depending on their device's screen size",
      "See hover states for all interactive elements on the page",
      "Receive an error message when the form is submitted if:"
    ]
  },
  "./apps/newbie/meet-landing-page/": {
    "title": "Meet landing page solution",
    "bullets": [
      "Meet landing page solution"
    ]
  },
  "./apps/newbie/nft-preview-card-component/": {
    "title": "NFT preview card component solution",
    "bullets": [
      "View the optimal layout depending on their device's screen size",
      "See hover states for interactive elements",
      "### Screenshot"
    ]
  },
  "./apps/newbie/order-summary-component/": {
    "title": "Order summary card solution",
    "bullets": [
      "See hover states for interactive elements",
      "### Screenshot",
      "## ⚙️ My process"
    ]
  },
  "./apps/newbie/pod-request-access-landing-page/": {
    "title": "Pod request access landing page solution",
    "bullets": [
      "View the optimal layout depending on their device's screen size",
      "See hover states for interactive elements",
      "Receive an error message when the form is submitted if:"
    ]
  },
  "./apps/newbie/product-preview-card-component/": {
    "title": "Product preview card component solution",
    "bullets": [
      "Product preview card component solution"
    ]
  },
  "./apps/newbie/profile-card-component/": {
    "title": "Profile card component solution",
    "bullets": [
      "Profile card component solution"
    ]
  },
  "./apps/newbie/qr-code-component/": {
    "title": "QR code component solution",
    "bullets": [
      "QR code component solution"
    ]
  },
  "./apps/newbie/recipe-page/": {
    "title": "Recipe page solution",
    "bullets": [
      "Recipe page solution"
    ]
  },
  "./apps/newbie/result-summary-component/": {
    "title": "Results summary component solution",
    "bullets": [
      "View the optimal layout for the interface depending on their device's screen size",
      "See hover and focus states for all interactive elements on the page",
      "Bonus: Use the local JSON data to dynamically populate the content"
    ]
  },
  "./apps/newbie/single-price-grid-component/": {
    "title": "Single price grid component solution",
    "bullets": [
      "View the optimal layout for the component depending on their device's screen size",
      "See a hover state on desktop for the Sign Up call-to-action",
      "### Screenshot"
    ]
  },
  "./apps/newbie/skilled-elearning-landing-page/": {
    "title": "Skilled e-learning landing page solution",
    "bullets": [
      "View the optimal layout depending on their device's screen size",
      "See hover states for interactive elements",
      "### Screenshot"
    ]
  },
  "./apps/newbie/social-link-profile/": {
    "title": "Social links profile solution",
    "bullets": [
      "Social links profile solution"
    ]
  },
  "./apps/newbie/social-proof-section/": {
    "title": "Social proof section solution",
    "bullets": [
      "View the optimal layout for the section depending on their device's screen size",
      "### Screenshot",
      "### Links"
    ]
  },
  "./apps/newbie/stats-preview-card-component/": {
    "title": "Stats preview card component solution",
    "bullets": [
      "View the optimal layout depending on their device's screen size",
      "### Screenshot",
      "### Links"
    ]
  },
  "./apps/newbie/workit-landing-page/": {
    "title": "Workit landing page solution",
    "bullets": [
      "View the optimal layout for the interface depending on their device's screen size",
      "See hover and focus states for all interactive elements on the page",
      "### Screenshot"
    ]
  }
}